fuzzytrie-0.3.0.dist-info/METADATA
fuzzytrie-0.3.0.dist-info/WHEEL
fuzzytrie/__init__.py
fuzzytrie/fuzzytrie.cpython-311-darwin.so
fuzzytrie-0.3.0.dist-info/RECORD
